tdo/__init__.py
tdo/main.py
tdo/todolist/__init__.py
tdo/todolist/export.py
tdo/todolist/help.py
tdo/todolist/listing.py
tdo/todolist/listmanagement.py
tdo/todolist/maintenance.py
tdo/todolist/persistence.py
tdo/todolist/printing.py
tdo/todolist/theme.py
tdo-1.1.3.dist-info/DESCRIPTION.rst
tdo-1.1.3.dist-info/METADATA
tdo-1.1.3.dist-info/RECORD
tdo-1.1.3.dist-info/WHEEL
tdo-1.1.3.dist-info/entry_points.txt
tdo-1.1.3.dist-info/metadata.json
tdo-1.1.3.dist-info/top_level.txt
tests/__init__.py
tests/export_test.py
tests/file_test.py
