Metadata-Version: 2.0
Name: tdo
Version: 1.1.3
Summary: A todo list tool for the terminal.
Home-page: UNKNOWN
Author: tdolist
Author-email: UNKNOWN
License: MIT
Platform: UNKNOWN
